neuroboros/__init__.py
neuroboros/_version.py
neuroboros/benchmark.py
neuroboros/glm.py
neuroboros/io.py
neuroboros/linalg.py
neuroboros/plot2d.py
neuroboros/plot_mebrains.py
neuroboros/searchlights.py
neuroboros/spaces.py
neuroboros/stats.py
neuroboros/datasets/__init__.py
neuroboros/datasets/camcan_bang.txt
neuroboros/datasets/camcan_rest.txt
neuroboros/datasets/camcan_smt.txt
neuroboros/surface/__init__.py
neuroboros/surface/_barycentric.py
neuroboros/surface/areal.py
neuroboros/surface/barycentric.py
neuroboros/surface/dijkstra.py
neuroboros/surface/nnfr.py
neuroboros/surface/properties.py
neuroboros/surface/subdivision.py
neuroboros/surface/union.py
neuroboros/surface/voronoi.py
neuroboros/utils/__init__.py
neuroboros-0.1.9.data/scripts/npls
neuroboros-0.1.9.data/scripts/rmdirs
neuroboros-0.1.9.dist-info/LICENSE
neuroboros-0.1.9.dist-info/METADATA
neuroboros-0.1.9.dist-info/WHEEL
neuroboros-0.1.9.dist-info/top_level.txt
neuroboros-0.1.9.dist-info/RECORD
