Metadata-Version: 2.1
Name: neuroboros
Version: 0.1.9
Summary: Neuroimaging analysis in Python
Author-email: Ma Feilong <mafeilong@gmail.com>
License: MIT License
Project-URL: Homepage, https://neuroboros.github.io/
Project-URL: Bug Tracker, https://github.com/neuroboros/neuroboros/issues
Classifier: Programming Language :: Python :: 3
Classifier: Programming Language :: Python :: 3 :: Only
Classifier: License :: OSI Approved :: MIT License
Classifier: Operating System :: OS Independent
Classifier: Intended Audience :: Science/Research
Classifier: Topic :: Scientific/Engineering
Requires-Python: >=3.6
License-File: LICENSE
Requires-Dist: numpy
Requires-Dist: scipy
Requires-Dist: nibabel
Requires-Dist: requests
Requires-Dist: joblib
Requires-Dist: pandas
Requires-Dist: Pillow
Requires-Dist: matplotlib
Provides-Extra: extra
Requires-Dist: neuroboros-extra ; extra == 'extra'
Provides-Extra: full
Requires-Dist: datalad ; extra == 'full'
Requires-Dist: neuroboros-extra ; extra == 'full'
Provides-Extra: test
Requires-Dist: pytest ; extra == 'test'
